pyrandomart/__init__.py
pyrandomart/pyrandomart.py
pyrandomart/version.py
pyrandomart-1.1.2.dist-info/licenses/LICENSE
pyrandomart-1.1.2.dist-info/METADATA
pyrandomart-1.1.2.dist-info/WHEEL
pyrandomart-1.1.2.dist-info/top_level.txt
pyrandomart-1.1.2.dist-info/RECORD
