Metadata-Version: 2.4
Name: pyrandomart
Version: 1.1.2
Summary: Python library to generate randomart of a bytes string
Author-email: "Aaron M." <aaronm6@gmail.com>
License-Expression: MIT
Project-URL: Homepage, https://github.com/aaronm6/pyrandomart
Project-URL: Repository, https://github.com/aaronm6/pyrandomart
Platform: unix-like
Classifier: Programming Language :: Python :: 3
Requires-Python: >=3.9.0
License-File: LICENSE
Dynamic: license-file
